pkgschema/__init__.py
pkgschema/schemas/copy-object.json
pkgschema/schemas/definitions.json
pkgschema/schemas/flash-object.json
pkgschema/schemas/imxkobs-object.json
pkgschema/schemas/install-if-different.json
pkgschema/schemas/metadata.json
pkgschema/schemas/raw-object.json
pkgschema/schemas/tarball-object.json
pkgschema/schemas/ubifs-object.json
updatehub_package_schema-1.0.0a3.dist-info/DESCRIPTION.rst
updatehub_package_schema-1.0.0a3.dist-info/METADATA
updatehub_package_schema-1.0.0a3.dist-info/RECORD
updatehub_package_schema-1.0.0a3.dist-info/WHEEL
updatehub_package_schema-1.0.0a3.dist-info/metadata.json
updatehub_package_schema-1.0.0a3.dist-info/top_level.txt
