Metadata-Version: 2.0
Name: updatehub-package-schema
Version: 1.0.0a3
Summary: UpdateHub package schema validator for Python
Home-page: http://www.ossystems.com.br
Author: O.S. Systems Software LTDA
Author-email: contato@ossystems.com.br
License: MIT
Platform: UNKNOWN
Requires-Dist: jsonschema (>=2.3.0)
Requires-Dist: rfc3987 (>=1.3)
